excel_database/__init__.py
excel_database/database.py
excel_database-1.0.1.dist-info/licenses/LICENSE
excel_database-1.0.1.dist-info/METADATA
excel_database-1.0.1.dist-info/WHEEL
excel_database-1.0.1.dist-info/top_level.txt
excel_database-1.0.1.dist-info/RECORD
