Metadata-Version: 2.4
Name: excel-database
Version: 1.0.1
Summary: Lightweight Excel-based CRUD database using openpyxl
Author-email: whitespaca <whitespaca@outlook.com>
License: MIT
Keywords: excel,database,crud,openpyxl
Classifier: Programming Language :: Python :: 3.7
Classifier: Programming Language :: Python :: 3.8
Classifier: Programming Language :: Python :: 3.9
Classifier: Programming Language :: Python :: 3.10
Classifier: Programming Language :: Python :: 3.11
Classifier: Operating System :: OS Independent
Requires-Python: >=3.7
License-File: LICENSE
Requires-Dist: openpyxl>=3.0
Dynamic: license-file
